stream2/BranchNode.py
stream2/CreateItem.py
stream2/OnItem.py
stream2/Uni.py
stream2/__init__.py
test/test01.py
stream2-0.0.3.dist-info/LICENSE
stream2-0.0.3.dist-info/METADATA
stream2-0.0.3.dist-info/WHEEL
stream2-0.0.3.dist-info/top_level.txt
stream2-0.0.3.dist-info/RECORD
